yolo2labelme.py
yolo2labelme-0.0.7.dist-info/LICENSE
yolo2labelme-0.0.7.dist-info/METADATA
yolo2labelme-0.0.7.dist-info/WHEEL
yolo2labelme-0.0.7.dist-info/entry_points.txt
yolo2labelme-0.0.7.dist-info/top_level.txt
yolo2labelme-0.0.7.dist-info/RECORD
