Metadata-Version: 2.1
Name: yolo2labelme
Version: 0.0.7
Summary: Tool to convert yolo format dataset to labelme json format.
Author-email: Kadapalla Nithin Kumar <kadapallanithin@gmail.com>
Project-URL: Homepage, https://github.com/kadapallaNithin/yolo2labelme
Project-URL: Bug Tracker, https://github.com/kadapallaNithin/yolo2labelme/issues
Classifier: Programming Language :: Python :: 3
Classifier: License :: OSI Approved :: MIT License
Classifier: Operating System :: OS Independent
Requires-Python: >=3.7
License-File: LICENSE
Requires-Dist: Pillow
Requires-Dist: PyYAML
